<?xml version='1.0' encoding='UTF-8'?>
<tei.2>
    <teiHeader xml:lang="pt"></teiHeader>
    <text>

        <pb xml:id="pag1" />
            <!-- folha em branco, sem nenhuma informação -->

        <pb xml:id="pag2" />
            <selo>
                <item1>Nº - 16 -</item1>
                <item2>- 1884 -</item2>
            </selo>
            <destinatario>
                <choice>
                    <abbr>Ex.<sup>mo</sup></abbr>
                    <expan>Excelentíssimo</expan>
                </choice>
                mestre e ami
            </destinatario>
            <data when = "20-06-1884">20/06/1884</data>
            <placeName>Lamego,</placeName>

            <p xml:id="paragrafo_1">    
                <l>Talvez que na verdades.Fialho</l><lb />
                <l>não tivesse intenção de me beliscar;</l><lb />
                <l>a minha impressão porêm, ao acabar</l><lb />
                <l>de lêr-lho o folhetim, feito de mais a</l><lb />
                <l>mais depois do meu, foi de que elle</l><lb />
                <l>era uma resposta e um desforço. E</l><lb />
                <l>porcerto não deixa de entender-se prin<pc force="inter">-</pc></l><lb />
                <l>cipalmente comigo aquele epitheto de</l><lb />
                <l><emph rend="underline">velho precosissismo </emph>, bem como a insidia</l><lb />
                <l>do meu appellido embrulhado no <emph rend="underline">con</emph><pc force="inter">-</pc></l><lb />
                <l><emph rend="underline">selheira</emph> do <emph rend="underline">primo Bazilio</emph>.</l><lb />
            </p>

            <p xml:id="paragrafo_2"> 
                <l>Não sou purista; falta-me a</l><lb />
                <l>auctoridade e a estudo. Acudo porêm par</l><lb />
                <l>elles, indignado</l>
            </p>
        

        <pb xml:id="pag3" />
            <p xml:id="paragrafo_3">
                <l>Fêz-me intensos pruridos de cu<pc force="inter">-</pc></l><lb />
                <l>riosidade a sua comunicação, respeito</l><lb />
                <l>ao tal Sr. Ignácio da Silva, de quem</l><lb />
                <l>nunca li palavra. Vou procurar obter</l><lb />
                <l>alguma coisa d'elle, e sobretudo o que a</l><pc force="inter">-</pc><lb />
                <l>caso haja que me toque pela porta.</l>
            </p>

            <p xml:id="paragrafo_4">
                <l>Esta minha carta hoje é par<pc force="inter">-</pc></l><lb />
                <l>ticularmente de gratidão pela ines<pc force="inter">-</pc></l><lb />
                <l>gotavel bonhomia do meu amigo, sem<pc force="inter">-</pc></l><lb />
                <l>pre prompto a responder a quem tan<pc force="inter">-</pc></l><lb />
                <l>to, e tão repetido, o importuna.</l>
            </p>
            
            <p xml:id="paragrafo_5">
                <l>Ao mesmo tempo, quero apres<pc force="inter">-</pc></l><lb />
                <l>sar-me a communicar-lhes que, se a<pc force="inter">-</pc></l><lb />
                <l>caso voltar deve ao <placeName where='Porto, Portugal'>Porto</placeName>, se não dê</l><lb />
                <l>a canieira de ir a <placeName where='Mattosinhos, Portugal'>Mattosinhos</placeName>
                para</l>
                <!-- parágrafo continua na página seguinte -->
            </p>

        <pb xml:id="pag4" style="page-break-after: always; break-after: page;"/>
            <p xml:id="paragrafo_6">
                <l>me vêr, porque eu retirei d'ali no</l><lb />
                <l>salbado, a vir executar os meus traba<pc force="inter">-</pc></l><lb />
                <l>lhos de campo officiais, tenho anda<pc force="inter">-</pc></l><lb />
                <l>do pela Vouga, e só para meiado de</l><lb />
                <l>agosto voltarei áquella praia, a passar</l><lb />
                <l>ali a estação balnear.</l>
            </p>

            <p xml:id="paragrafo_7">
                <l>Mas por então espero, ainda assim,</l><lb />
                <l>ter a haura d'uma entrevista com</l><lb />
                <l>V-se.a, antes do meu regresso á</l><lb />
                <l>capital.</l>
            </p>
            

            <closer>
                <salute>
                    Seu
                    <choice>
                        <abbr>m.
                            <sup>to</sup>
                        </abbr>
                        <expan>muito</expan>
                    </choice>
                    dedicado<lb />
                    e admirador
                </salute>
            </closer>

            <note>
                <!-- texto escrito na diagonal ao lado do remetente e assinatura -->
                <l>N'este intervallo,</l><lb />
                <l>é-me dirigida a</l><lb />
                <l>correspondencia</l><lb />
                <l>pra Lamego,</l><lb />
                <l>aonde venho</l><lb />
                <l>de qd em qdo</l>
            </note>

            <author>
                <signed>AbelAcacio</signed>
            </author>
    </text>
</tei.2>